LICENSE
MANIFEST.in
README.md
setup.py
exploitdb/__init__.py
exploitdb/cli.py
exploitdb.egg-info/PKG-INFO
exploitdb.egg-info/SOURCES.txt
exploitdb.egg-info/dependency_links.txt
exploitdb.egg-info/entry_points.txt
exploitdb.egg-info/not-zip-safe
exploitdb.egg-info/top_level.txt
tests/__init__.py