Metadata-Version: 1.1
Name: exploitdb
Version: 0.0.6
Summary: 个人研究使用
Home-page: https://github.com/hello/exploitdb
Author: hello
Author-email: hello@hello.com
License: Apache Software License 2.0
Keywords: exploitdb
Platform: UNKNOWN
Classifier: Development Status :: 5 - Production/Stable
Classifier: Intended Audience :: Developers
Classifier: License :: OSI Approved :: Apache Software License
Classifier: Natural Language :: English
Classifier: Programming Language :: Python
Classifier: Programming Language :: Python :: 2
Classifier: Programming Language :: Python :: 2.7
Classifier: Programming Language :: Python :: 3
Classifier: Programming Language :: Python :: 3.4
Classifier: Programming Language :: Python :: 3.5
Classifier: Programming Language :: Python :: 3.6
